[{"s": "tsentralnoe-otverstie-logan", "t": "Центральное отверстие в ступице Logan: размеры, замена, ошибки", "i": "📁", "c": "logan"}, {"s": "tsilindr-stsepleniya-reno-megan-2", "t": "Цилиндр сцепления Renault Megane 2: признаки неисправности и замена", "i": "📁", "c": "megane"}, {"s": "tso-logan-1", "t": "ЦО Logan 1: полное руководство по диагностике и ремонту", "i": "📁", "c": "logan"}, {"s": "tsvet-b66-reno-logan", "t": "Цвет B66 у Renault Logan: код, особенности и выбор для покраски", "i": "📁", "c": "logan"}, {"s": "tsilindr-zadnij-reno-logan", "t": "Задний цилиндр сцепления Renault Logan: выбор, замена, неисправности", "i": "📁", "c": "logan"}, {"s": "tsilindr-tormoznoj-zadnij-daster-4kh4-artikul", "t": "Задний тормозной цилиндр Duster 4x4: артикул, выбор и замена", "i": "📁", "c": "duster"}, {"s": "tsilindr-tormoznoj-zadnij-daster", "t": "Задний тормозной цилиндр Duster: выбор, замена, неисправности", "i": "📁", "c": "duster"}, {"s": "tsilindr-stsepleniya-reno-stsenik-2", "t": "Цилиндр сцепления Renault Scenic 2: признаки неисправности и замена", "i": "📁", "c": "scenic"}, {"s": "tsvet-kuzova-reno-daster", "t": "Цвета кузова Renault Duster: официальные оттенки и выбор для покупки", "i": "📁", "c": "duster"}, {"s": "tsekbs-reno-daster", "t": "ЦЭКБС Renault Duster: что это, как сбросить и устранить ошибки", "i": "📁", "c": "duster"}, {"s": "tsentralnoe-otverstie-reno-logan-2", "t": "Центральное отверстие в Renault Logan 2: размеры, замена, советы", "i": "📁", "c": "logan"}, {"s": "tsentralnaya-konsol-reno-logan", "t": "Центральная консоль Renault Logan: устройство, ремонт и тюнинг", "i": "📁", "c": "logan"}, {"s": "tsilindr-tormoznoj-zadnij-reno-logan-2", "t": "Задний тормозной цилиндр Renault Logan 2: выбор, замена, неисправности", "i": "📁", "c": "logan"}, {"s": "tsekbs-reno-logan-1", "t": "ЦЭКБС Renault Logan 1: расшифровка, неисправности и ремонт", "i": "📁", "c": "logan"}, {"s": "tsekbs-reno-megan-2-chto-eto", "t": "ЦЭКБС Renault Megane 2: что это, как работает и где находится", "i": "📁", "c": "megane"}, {"s": "tsilindr-stsepleniya-daster", "t": "Цилиндр сцепления Дастер: признаки неисправности и замена", "i": "📁", "c": "duster"}, {"s": "tsurinoya-ofitsialnyj-sajt", "t": "Цуриноя официальный сайт: где найти, как пользоваться и что важно знать", "i": "📁", "c": "drugoe"}, {"s": "tsarskaya-ukha-na-kurinom-bulone", "t": "Царская уха на курином бульоне: рецепт с фото и секретами приготовления", "i": "📁", "c": "drugoe"}, {"s": "tseny-na-reno-logan-bu", "t": "Цены на Renault Logan б/у 2026: анализ рынка и советы по покупке", "i": "📁", "c": "logan"}, {"s": "tsilindr-stsepleniya-megan-2", "t": "Цилиндр сцепления Renault Megane 2: признаки неисправности и замена", "i": "📁", "c": "megane"}, {"s": "tso-reno-sandero", "t": "ЦО Renault Sandero: как проверить историю и избежать проблем", "i": "📁", "c": "sandero"}, {"s": "tsveta-reno-kaptur", "t": "Цвета Renault Kaptur 2026: палитра, фото, выбор и особенности", "i": "📁", "c": "kaptur"}, {"s": "tsapfa-zadnyaya-reno-daster-4-kh-4", "t": "Задняя цапфа Renault Duster 4x4: выбор, замена, неисправности", "i": "📁", "c": "duster"}, {"s": "tsentralnoe-otverstie-diska-reno-logan-1", "t": "Центральное отверстие диска Renault Logan 1: размеры, подбор, советы", "i": "📁", "c": "logan"}, {"s": "tsentralnyj-zamok-reno-simbol", "t": "Центральный замок Renault Symbol: неисправности и ремонт", "i": "📁", "c": "symbol"}, {"s": "tsilindr-tormoznoj-zadnij-reno-logan-1", "t": "Задний тормозной цилиндр Renault Logan 1: выбор, замена, неисправности", "i": "📁", "c": "logan"}, {"s": "tso-reno-daster", "t": "ЦО Рено Дастер: где находится, как расшифровать и проверить", "i": "📁", "c": "duster"}, {"s": "tsvet-676-reno", "t": "Код цвета 676 у Renault: расшифровка, аналоги, как подобрать краску", "i": "📁", "c": "logan"}, {"s": "tsentralnyj-tros-ruchnika-reno-logan", "t": "Центральный трос ручника Renault Logan: замена, регулировка, неисправности", "i": "📁", "c": "logan"}, {"s": "tsentralnoe-otverstie-reno-daster", "t": "Центральное отверстие в ступице Renault Duster: размеры, замена, советы", "i": "📁", "c": "duster"}, {"s": "tsilindr-tormoznoj-zadnij-logan-artikul", "t": "Задний тормозной цилиндр Logan: артикулы, выбор и замена", "i": "📁", "c": "logan"}, {"s": "tso-logan-2", "t": "Renault Logan 2: обзор, характеристики и секреты эксплуатации", "i": "📁", "c": "logan"}, {"s": "tsveta-reno-logan-1-pokoleniya", "t": "Цвета Renault Logan 1 поколения: палитра, коды, особенности выбора", "i": "📁", "c": "logan"}, {"s": "tsekbs-reno-flyuens", "t": "ЦЭКБС Renault Fluence: расшифровка, сброс и диагностика ошибок", "i": "📁", "c": "fluence"}, {"s": "tsentralnoe-otverstie-diska-reno-logan-2", "t": "Центральное отверстие диска Renault Logan 2: размеры, подбор, нюансы", "i": "📁", "c": "logan"}, {"s": "tsifry-kotorye-prinosyat-dengi-i-udachu", "t": "Цифры, которые приносят деньги и удачу: нумерология для бизнеса и жизни", "i": "📁", "c": "drugoe"}, {"s": "tsilindr-tormoznoj-zadnij-reno-simbol", "t": "Задний тормозной цилиндр Renault Symbol: выбор, замена, неисправности", "i": "📁", "c": "symbol"}, {"s": "tsokol-lamp-reno-logan-2", "t": "Цоколь ламп Renault Logan 2: таблица совместимости и замена", "i": "📁", "c": "logan"}, {"s": "tsentralnoe-otverstie-daster", "t": "Центральное отверстие в ступице Duster: размеры, замена, советы", "i": "📁", "c": "duster"}, {"s": "tsentralnyj-tros-ruchnika-reno-daster", "t": "Центральный трос ручника Renault Duster: замена, регулировка, неисправности", "i": "📁", "c": "duster"}, {"s": "tsilindr-tormoznoj-zadnij-daster-4kh4", "t": "Задний тормозной цилиндр Duster 4x4: выбор, замена, неисправности", "i": "📁", "c": "duster"}, {"s": "tseny-na-novyj-reno-daster", "t": "Цены на новый Renault Duster 2026: комплектации, скидки, где купить дешевле", "i": "📁", "c": "duster"}, {"s": "tso-reno-flyuens", "t": "ЦО Рено Флюенс: как проверить историю, расшифровать VIN и избежать обмана", "i": "📁", "c": "fluence"}, {"s": "tsentralnoe-otverstie-reno-sandero", "t": "Центральное отверстие в ступице Renault Sandero: размеры и нюансы", "i": "📁", "c": "sandero"}, {"s": "tsilindr-stsepleniya-reno-daster", "t": "Цилиндр сцепления Renault Duster: признаки неисправности и замена", "i": "📁", "c": "duster"}, {"s": "tsilindr-tormoznoj-daster", "t": "Тормозной цилиндр Duster: признаки неисправности и замена", "i": "📁", "c": "duster"}, {"s": "tsilindr-tormoznoj-zadnij-reno-daster", "t": "Задний тормозной цилиндр Renault Duster: выбор, замена, неисправности", "i": "📁", "c": "duster"}, {"s": "tso-diska-reno-daster", "t": "ЦО диска Renault Duster: размеры, параметры и совместимость", "i": "📁", "c": "duster"}, {"s": "tsvet-reno-logan-1-palitra-tsvetov", "t": "Палитра цветов Renault Logan 1: официальные оттенки и их особенности", "i": "📁", "c": "logan"}, {"s": "tso-reno-logan", "t": "ЦО Рено Логан: как проверить, где находится и что делать при ошибках", "i": "📁", "c": "logan"}, {"s": "tso-reno-megan-2", "t": "ЦО Рено Меган 2: где найти, как проверить и что делать при ошибках", "i": "📁", "c": "megane"}, {"s": "tsvet-murenovyj-eto-kakoj", "t": "Муреновый цвет — что это за оттенок? Отличия от бордового и фиолетового", "i": "📁", "c": "drugoe"}, {"s": "tsveta-logan-1-restajling", "t": "Цвета Renault Logan 1 рестайлинг: официальные оттенки и выбор", "i": "📁", "c": "logan"}, {"s": "tsvetovaya-gamma-reno-daster", "t": "Цвета Renault Duster 2026: официальная палитра, фото и выбор оттенка", "i": "📁", "c": "duster"}, {"s": "tsvet-ted69-renault", "t": "Цвет TED69 Renault: код, особенности и как выбрать для вашего авто", "i": "📁", "c": "drugoe"}, {"s": "tsentralnoe-otverstie-diska-reno-logan", "t": "Центральное отверстие диска Renault Logan: размеры, подбор, ошибки", "i": "📁", "c": "logan"}, {"s": "tsilindr-tormoznoj-reno-simbol", "t": "Тормозной цилиндр Renault Symbol: неисправности, замена, выбор", "i": "📁", "c": "symbol"}, {"s": "tsyplenok-tabaka-kak-zamarinovat", "t": "Цыпленок табака: 5 проверенных рецептов маринада для сочной корочки", "i": "📁", "c": "drugoe"}, {"s": "tsekbs-reno-megan-2-gde-nakhoditsya", "t": "ЦЭКБС Renault Megane 2: где находится блок и как его проверить", "i": "📁", "c": "megane"}, {"s": "tso-reno-kaptur", "t": "ЦО Renault Kaptur: где находится, как проверить и расшифровать коды ошибок", "i": "📁", "c": "kaptur"}, {"s": "tsekbs-reno-logan-2", "t": "ЦЭКБС Renault Logan 2: что это, как сбросить и устранить ошибки", "i": "📁", "c": "logan"}, {"s": "tsentralnoe-otverstie-reno-logan-1", "t": "Центральное отверстие диска Renault Logan 1: размеры, подбор, нюансы", "i": "📁", "c": "logan"}, {"s": "tsvet-reno-logan-sinij", "t": "Синий Renault Logan: оттенки, коды краски и выбор цвета (2026)", "i": "📁", "c": "logan"}, {"s": "tsilindr-tormoznoj-zadnij-pravyj-reno-daster-4kh4-artikul", "t": "Задний правый тормозной цилиндр Renault Duster 4x4: артикул, замена, выбор", "i": "📁", "c": "duster"}, {"s": "tso-reno-logan-2", "t": "ЦО Рено Логан 2: цены, особенности и как выбрать лучший вариант", "i": "📁", "c": "logan"}, {"s": "tsvet-laguna-vaz", "t": "Цвет Лагуна ВАЗ: коды, особенности и как выбрать оригинал", "i": "📁", "c": "laguna"}, {"s": "tsentralnoe-otverstie-diska-reno-logan-1-pokoleniya", "t": "Центральное отверстие диска Renault Logan 1: размеры, подбор, ошибки", "i": "📁", "c": "logan"}, {"s": "tsentralnoe-otverstie-reno-kaptur", "t": "Центральное отверстие Renault Kaptur: размеры, замена и особенности", "i": "📁", "c": "kaptur"}, {"s": "tsentralnyj-zamok-na-reno-logan-1", "t": "Центральный замок Renault Logan 1: ремонт, схема, неисправности", "i": "📁", "c": "logan"}, {"s": "tsinkuyut-li-kuzov-dastera", "t": "Цинкуют ли кузов Дастера? Ответ эксперта + проверка защиты", "i": "📁", "c": "duster"}, {"s": "tsvet-reno-sandero-stepvej-2", "t": "Цвета Renault Sandero Stepway 2: палитра, выбор и особенности", "i": "📁", "c": "sandero"}, {"s": "tsekbs-reno-megan-2", "t": "ЦЭКСБС Рено Меган 2: Диагностика, замена и кодирование блока", "i": "📁", "c": "megane"}, {"s": "tsveta-kuzova-reno-kaptur", "t": "Все цвета кузова Рено Каптур: палитра, выбор и нюансы окраски", "i": "📁", "c": "kaptur"}, {"s": "tsentralnoe-otverstie-logan-1", "t": "Центральное отверстие диска Logan 1: Размеры, параметры и замена", "i": "📁", "c": "logan"}, {"s": "tsentralnoe-otverstie-reno-megan-2", "t": "Центральное отверстие Рено Меган 2: Размеры, диск и установка колес", "i": "📁", "c": "megane"}, {"s": "tsilindr-zadnij-tormoznoj-reno-logan", "t": "Задний тормозной цилиндр Рено Логан: замена, признаки неисправности, выбор", "i": "📁", "c": "logan"}, {"s": "tsveta-kuzova-reno-daster", "t": "Цвета кузова Рено Дастер: Полная палитра, коды красок и выбор оттенка", "i": "📁", "c": "duster"}, {"s": "tsentralnoe-otverstie-diska-reno-megan-2", "t": "Центральное отверстие диска Рено Меган 2: размер, посадка и подбор колпаков", "i": "📁", "c": "megane"}, {"s": "tsentralnoe-otverstie-reno-logan", "t": "Центральное отверстие RENAULT LOGAN: размеры, колпачки и диски", "i": "📁", "c": "logan"}, {"s": "tso-na-reno-daster", "t": "Что такое CCO на Renault Duster: Расшифровка и решение проблем", "i": "📁", "c": "duster"}, {"s": "tsveta-provodov-reno", "t": "Распиновка и цвета проводов Renault: полная таблица цветов", "i": "📁", "c": "drugoe"}, {"s": "tsentralnyj-tonnel-logan-2", "t": "Центральный тоннель Логан 2: устройство, ремонт и тюнинг", "i": "📁", "c": "logan"}, {"s": "tsvetovaya-markirovka-pruzhin-reno", "t": "Цветовая маркировка пружин Рено: расшифровка, подбор и замена", "i": "📁", "c": "drugoe"}, {"s": "tsyplenok-tabaka-kak-marinovat", "t": "Цыпленок табака: идеальный маринад и секреты приготовления", "i": "📁", "c": "drugoe"}, {"s": "tsekbs-reno-laguna-2", "t": "ЦЭКБС Renault Laguna 2: Диагностика, ремонт и замена блока", "i": "📁", "c": "laguna"}, {"s": "tsveta-reno-daster-2013", "t": "Все цвета Renault Duster 2013: палитра, каталог и особенности подбора", "i": "📁", "c": "duster"}, {"s": "tsekbs-reno-chto-eto", "t": "ЦЭКБС Рено: что это, назначение и как сбросить ошибку", "i": "📁", "c": "drugoe"}, {"s": "tsokol-lamp-reno-daster", "t": "Цоколь ламп Рено Дастер: полная таблица и замена света", "i": "📁", "c": "duster"}, {"s": "tsentralnoe-otverstie-diska-reno-sandero", "t": "Центральное отверстие диска Рено Сандеро: размеры, посадка и замена", "i": "📁", "c": "sandero"}, {"s": "tso-reno-sandero-1", "t": "Рено Сандеро 1: Полный разбор модели, технические характеристики и нюансы эксплуатации", "i": "📁", "c": "sandero"}, {"s": "tsveta-reno-sandero-1", "t": "Палитра цветов Renault Sandero 1: Коды, названия и особенности", "i": "📁", "c": "sandero"}, {"s": "tsentralnaya-konsol-reno-logan-2", "t": "Центральная консоль Рено Логан 2: обзор, мультимедиа, тюнинг и ремонт", "i": "📁", "c": "logan"}, {"s": "tsentralnoe-otverstie-na-diskakh-reno-logan", "t": "Центральное отверстие дисков Рено Логан: размер, разболтовка и установка", "i": "📁", "c": "logan"}, {"s": "tsilindr-tormoznoj-zadnij-logan-2", "t": "Цилиндр тормозной задний Логан 2: замена, признаки поломки, каталожные номера", "i": "📁", "c": "logan"}, {"s": "tso-reno-logan-1", "t": "Ремонт и эксплуатация двигателя К4М на Renault Logan 1: Полное руководство", "i": "📁", "c": "logan"}, {"s": "tsvetovye-metki-na-pruzhinakh-reno", "t": "Цветовые метки на пружинах Renault: расшифровка и подбор", "i": "📁", "c": "duster"}, {"s": "tsentralnoe-otverstie-diska-logan", "t": "Центральное отверстие диска Рено Логан: размеры, центровка и ошибки", "i": "📁", "c": "logan"}, {"s": "tsilindr-tormoznoj-zadnij-logan", "t": "Задний тормозной цилиндр Logan: Замена, признаки неисправности и выбор", "i": "📁", "c": "logan"}, {"s": "tso-megan-2", "t": "Renault Megane 2: Полное руководство по диагностике и ремонту", "i": "📁", "c": "megane"}, {"s": "tskbs-reno-chto-eto", "t": "ЦКБС Рено: что это, где находится и зачем нужна эта система", "i": "📁", "c": "авто"}, {"s": "tsvet-rnz-reno-logan", "t": "Цвета RNZ Renault Logan: палитра, коды красок и подбор", "i": "📁", "c": "logan"}, {"s": "tsentralnaya-konsol-logan-2", "t": "Центральная консоль Логан 2: Обзор, ремонт и тюнинг панели", "i": "📁", "c": "logan"}, {"s": "tsilindr-tormoznoj-zadnij-reno-logan", "t": "Задний тормозной цилиндр Рено Логан: замена, симптомы, выбор", "i": "📁", "c": "logan"}, {"s": "tsilindr-stsepleniya-reno-megan-3", "t": "Цилиндр сцепления Рено Меган 3: Признаки, выбор и замена", "i": "📁", "c": "megane"}, {"s": "tso-reno-megan-3", "t": "ЦО Рено Меган 3: Полный гид по замене и ремонту центрального замка", "i": "📁", "c": "megane"}, {"s": "tsurinoya-yaguar-1000", "t": "Обзор катушечного спиннинга Tsurinoya Jaguar 1000: Характеристики и Тест", "i": "📁", "c": "drugoe"}, {"s": "tsveta-reno-logan-1-restajling", "t": "Все цвета Renault Logan 1 рестайлинг: палитра, коды краски и фото", "i": "📁", "c": "logan"}, {"s": "tsveta-reno-megan-2", "t": "Цвета Renault Megane 2: Палитра, код краски и подбор", "i": "📁", "c": "megane"}, {"s": "tsentralnoe-otverstie-reno-flyuens", "t": "Центральное отверстие на колесе Renault Fluence: размеры и установка", "i": "📁", "c": "fluence"}, {"s": "tsilindr-zadnij-tormoznoj-logan", "t": "Цилиндр задний тормозной Логан: замена, симптомы, выбор", "i": "📁", "c": "logan"}, {"s": "tsentralnaya-konsol-reno-logan-1", "t": "Центральная консоль Рено Логан 1: замена, ремонт и тюнинг панели", "i": "📁", "c": "logan"}, {"s": "tseny-na-reno-arkana", "t": "Цены на Renault Arkana: актуальный прайс 2026, комплектации и советы", "i": "📁", "c": "arkana"}, {"s": "tsveta-reno-flyuens", "t": "Все цвета Renault Fluence: палитра, выбор и нюансы покраски", "i": "📁", "c": "fluence"}, {"s": "tsvetovaya-gamma-reno-logan", "t": "Полный обзор цветовой гаммы Renault Logan: коды красок и выбор оттенка", "i": "📁", "c": "logan"}, {"s": "tsentralnaya-konsol-reno-daster", "t": "Центральная консоль Renault Duster: обзор, ремонт и тюнинг", "i": "📁", "c": "duster"}, {"s": "tsentralnoe-otverstie-diska-reno-flyuens", "t": "Центральное отверстие диска Рено Флюенс: размеры, ступица и установка", "i": "📁", "c": "fluence"}, {"s": "tseny-na-avtomobili-reno", "t": "Цены на автомобили Рено: актуальный прайс, скидки и стоимость подержанных авто", "i": "📁", "c": "duster"}, {"s": "tsokol-lamp-reno-megan-2", "t": "Цоколь ламп Renault Megane 2: полная таблица и замена", "i": "📁", "c": "megane"}, {"s": "tsentralnyj-zamok-na-reno-logan", "t": "Центральный замок на Рено Логан: неисправности, ремонт и доработка", "i": "📁", "c": "logan"}, {"s": "tsep-grm-daster", "t": "Замена цепи ГРМ на Renault Duster: сроки, цены и нюансы", "i": "📁", "c": "duster"}, {"s": "tsilindr-perednij-tormoznoj-logan", "t": "Цилиндр переднего тормоза на Renault Logan: выбор, замена, цены", "i": "📁", "c": "logan"}, {"s": "tsveta-reno-sandero-stepvej-2", "t": "Палитра Renault Sandero Stepway 2: все цвета кузова и коды красок", "i": "📁", "c": "sandero"}]